setup.py
distributionsudacityexercise/Binomialdistribution.py
distributionsudacityexercise/Gaussiandistribution.py
distributionsudacityexercise/Generaldistribution.py
distributionsudacityexercise/__init__.py
distributionsudacityexercise.egg-info/PKG-INFO
distributionsudacityexercise.egg-info/SOURCES.txt
distributionsudacityexercise.egg-info/dependency_links.txt
distributionsudacityexercise.egg-info/not-zip-safe
distributionsudacityexercise.egg-info/top_level.txt